{
  "main": {
    "id": "188ca9f448e6dce6",
    "type": "split",
    "children": [
      {
        "id": "7d52657219bc3110",
        "type": "tabs",
        "children": [
          {
            "id": "08e1a55293396da9",
            "type": "leaf",
            "state": {
              "type": "markdown",
              "state": {
                "file": "1. - Основы ОС.md",
                "mode": "source",
                "source": false
              },
              "icon": "lucide-file",
              "title": "1. - Основы ОС"
            }
          }
        ]
      }
    ],
    "direction": "vertical"
  },
  "left": {
    "id": "7f7d854287cc6c75",
    "type": "split",
    "children": [
      {
        "id": "02f4914b05eaecf4",
        "type": "tabs",
        "children": [
          {
            "id": "e37965b05f8e2820",
            "type": "leaf",
            "state": {
              "type": "file-explorer",
              "state": {
                "sortOrder": "alphabetical",
                "autoReveal": false
              },
              "icon": "lucide-folder-closed",
              "title": "Файловый менеджер"
            }
          },
          {
            "id": "36e69cd028c830a1",
            "type": "leaf",
            "state": {
              "type": "search",
              "state": {
                "query": "",
                "matchingCase": false,
                "explainSearch": false,
                "collapseAll": false,
                "extraContext": false,
                "sortOrder": "alphabetical"
              },
              "icon": "lucide-search",
              "title": "Поиск"
            }
          },
          {
            "id": "07b58f692c04b020",
            "type": "leaf",
            "state": {
              "type": "bookmarks",
              "state": {},
              "icon": "lucide-bookmark",
              "title": "Закладки"
            }
          }
        ]
      }
    ],
    "direction": "horizontal",
    "width": 300,
    "collapsed": true
  },
  "right": {
    "id": "ca8348d92c13c097",
    "type": "split",
    "children": [
      {
        "id": "93da8cd390bf3ed9",
        "type": "tabs",
        "children": [
          {
            "id": "a94d35a7e8bfc35e",
            "type": "leaf",
            "state": {
              "type": "backlink",
              "state": {
                "file": "1. - Основы ОС.md",
                "collapseAll": false,
                "extraContext": false,
                "sortOrder": "alphabetical",
                "showSearch": false,
                "searchQuery": "",
                "backlinkCollapsed": false,
                "unlinkedCollapsed": true
              },
              "icon": "links-coming-in",
              "title": "Обратные ссылки для 1. - Основы ОС"
            }
          },
          {
            "id": "16819eef68e030c0",
            "type": "leaf",
            "state": {
              "type": "outgoing-link",
              "state": {
                "file": "1. - Основы ОС.md",
                "linksCollapsed": false,
                "unlinkedCollapsed": true
              },
              "icon": "links-going-out",
              "title": "Исходящие ссылки из 1. - Основы ОС"
            }
          },
          {
            "id": "610f69f0c0839e3d",
            "type": "leaf",
            "state": {
              "type": "tag",
              "state": {
                "sortOrder": "frequency",
                "useHierarchy": true,
                "showSearch": false,
                "searchQuery": ""
              },
              "icon": "lucide-tags",
              "title": "Теги"
            }
          },
          {
            "id": "b2753ab54533c2cc",
            "type": "leaf",
            "state": {
              "type": "all-properties",
              "state": {
                "sortOrder": "frequency",
                "showSearch": false,
                "searchQuery": ""
              },
              "icon": "lucide-archive",
              "title": "Все свойства"
            }
          },
          {
            "id": "b15dce0dedd9f94d",
            "type": "leaf",
            "state": {
              "type": "outline",
              "state": {
                "file": "1. - Основы ОС.md",
                "followCursor": false,
                "showSearch": false,
                "searchQuery": ""
              },
              "icon": "lucide-list",
              "title": "Структура 1. - Основы ОС"
            }
          }
        ]
      }
    ],
    "direction": "horizontal",
    "width": 300,
    "collapsed": true
  },
  "left-ribbon": {
    "hiddenItems": {
      "obsidian-git:Open Git source control": false,
      "switcher:Меню быстрого перехода": false,
      "graph:Граф": false,
      "canvas:Создать новый холст": false,
      "daily-notes:Сегодняшняя заметка": false,
      "templates:Вставить шаблон": false,
      "command-palette:Открыть палитру команд": false,
      "bases:Создать новую базу": false
    }
  },
  "active": "08e1a55293396da9",
  "lastOpenFiles": [
    "1. - Основы ОС.md"
  ]
}